votuderep/__init__.py
votuderep/__main__.py
votuderep/cli.py
votuderep/commands/__init__.py
votuderep/commands/derep.py
votuderep/commands/filter.py
votuderep/commands/getdbs.py
votuderep/commands/tabulate.py
votuderep/commands/trainingdata.py
votuderep/core/__init__.py
votuderep/core/blast.py
votuderep/core/dereplication.py
votuderep/core/filtering.py
votuderep/utils/__init__.py
votuderep/utils/io.py
votuderep/utils/logging.py
votuderep/utils/validators.py
votuderep-0.4.1.dist-info/licenses/LICENSE
votuderep-0.4.1.dist-info/METADATA
votuderep-0.4.1.dist-info/WHEEL
votuderep-0.4.1.dist-info/entry_points.txt
votuderep-0.4.1.dist-info/top_level.txt
votuderep-0.4.1.dist-info/RECORD
