Metadata-Version: 2.4
Name: votuderep
Version: 0.4.1
Summary: A CLI tool for dereplicating and filtering viral contigs
Author-email: Andrea Telatin <andrea.telatin@gmail.com>
License: MIT
Project-URL: Homepage, https://github.com/quadram-institute-bioscience/votuderep
Project-URL: Documentation, https://github.com/quadram-institute-bioscience/votuderep#readme
Project-URL: Repository, https://github.com/quadram-institute-bioscience/votuderep
Project-URL: Issues, https://github.com/quadram-institute-bioscience/votuderep/issues
Keywords: bioinformatics,viral,contigs,dereplication,blast
Classifier: Development Status :: 3 - Alpha
Classifier: Intended Audience :: Science/Research
Classifier: Topic :: Scientific/Engineering :: Bio-Informatics
Classifier: License :: OSI Approved :: MIT License
Classifier: Programming Language :: Python :: 3
Classifier: Programming Language :: Python :: 3.10
Classifier: Programming Language :: Python :: 3.11
Classifier: Programming Language :: Python :: 3.12
Requires-Python: >=3.10
License-File: LICENSE
Requires-Dist: rich>=13.0.0
Requires-Dist: rich-click>=1.7.0
Requires-Dist: pandas>=2.0.0
Requires-Dist: numpy>=1.24.0
Requires-Dist: pyfastx>=2.0.0
Provides-Extra: dev
Requires-Dist: pytest>=7.0.0; extra == "dev"
Requires-Dist: pytest-cov>=4.0.0; extra == "dev"
Requires-Dist: black>=23.0.0; extra == "dev"
Requires-Dist: ruff>=0.1.0; extra == "dev"
Dynamic: license-file
